README.rst
setup.py
canglong_client_tool.egg-info/PKG-INFO
canglong_client_tool.egg-info/SOURCES.txt
canglong_client_tool.egg-info/dependency_links.txt
canglong_client_tool.egg-info/requires.txt
canglong_client_tool.egg-info/top_level.txt
client_data_tool/__init__.py
client_data_tool/coluaco.py
client_data_tool/combine_lua_tool.py
client_data_tool/excel_lua_tools.py
client_data_tool/json_to_lua.py
client_data_tool/test.py
client_data_tool/upload_tool.py