Metadata-Version: 1.1
Name: canglong-client-tool
Version: 0.2.0
Summary: A data parsing tool for my project
Home-page: http://git.oschina.net/Mapz/canglong-client-tool
Author: Mapz Chen
Author-email: 61966578@qq.com
License: MIT
Platform: UNKNOWN
Classifier: Environment :: Console
Classifier: Intended Audience :: Developers
Classifier: Operating System :: OS Independent
Classifier: Topic :: Utilities
Classifier: Topic :: Software Development :: Libraries :: Python Modules
Classifier: Programming Language :: Python
Classifier: Programming Language :: Python :: 3
